teeth_gnashing/__init__.py
teeth_gnashing/client.py
teeth_gnashing/crypto_analysis.py
teeth_gnashing/server.py
teeth_gnashing-1.0.0.dist-info/licenses/LICENSE
teeth_gnashing-1.0.0.dist-info/METADATA
teeth_gnashing-1.0.0.dist-info/WHEEL
teeth_gnashing-1.0.0.dist-info/top_level.txt
teeth_gnashing-1.0.0.dist-info/RECORD
