Metadata-Version: 2.4
Name: teeth-gnashing
Version: 1.0.0
Summary: Production-ready Python library for dynamic snapshot-based encryption using server-client architecture
Author-email: Kirill Nikitenko <Cyan11777@gmail.com>
License: GPL-2.0
Project-URL: Homepage, https://github.com/username/teeth-gnashing
Project-URL: Documentation, https://github.com/username/teeth-gnashing#readme
Project-URL: Repository, https://github.com/username/teeth-gnashing.git
Project-URL: Issues, https://github.com/username/teeth-gnashing/issues
Keywords: encryption,cryptography,snapshot-based,server-client,security,hmac,key-derivation
Classifier: Development Status :: 4 - Beta
Classifier: Intended Audience :: Developers
Classifier: License :: OSI Approved :: GNU General Public License v2 (GPLv2)
Classifier: Operating System :: OS Independent
Classifier: Programming Language :: Python :: 3
Classifier: Programming Language :: Python :: 3.8
Classifier: Programming Language :: Python :: 3.9
Classifier: Programming Language :: Python :: 3.10
Classifier: Programming Language :: Python :: 3.11
Classifier: Programming Language :: Python :: 3.12
Classifier: Programming Language :: Python :: 3.13
Classifier: Topic :: Security :: Cryptography
Classifier: Topic :: Software Development :: Libraries :: Python Modules
Requires-Python: >=3.8
License-File: LICENSE
Requires-Dist: fastapi>=0.68.0
Requires-Dist: uvicorn[standard]>=0.15.0
Requires-Dist: aiohttp>=3.8.0
Requires-Dist: pydantic>=1.8.0
Requires-Dist: python-multipart>=0.0.5
Requires-Dist: python-jose[cryptography]>=3.3.0
Requires-Dist: cryptography>=41.0.0
Requires-Dist: blake3>=0.3.3
Provides-Extra: dev
Requires-Dist: pytest>=6.2.5; extra == "dev"
Requires-Dist: pytest-asyncio>=0.21.0; extra == "dev"
Requires-Dist: pytest-cov>=4.1.0; extra == "dev"
Requires-Dist: httpx>=0.23.0; extra == "dev"
Requires-Dist: black>=23.9.1; extra == "dev"
Requires-Dist: isort>=5.12.0; extra == "dev"
Requires-Dist: mypy>=1.5.1; extra == "dev"
Requires-Dist: pylint>=3.0.0; extra == "dev"
Dynamic: license-file
